colors.py
pygtails.py
testbed.py
pygtails-0.1.6.dist-info/DESCRIPTION.rst
pygtails-0.1.6.dist-info/METADATA
pygtails-0.1.6.dist-info/RECORD
pygtails-0.1.6.dist-info/WHEEL
pygtails-0.1.6.dist-info/metadata.json
pygtails-0.1.6.dist-info/top_level.txt
src/pygtails.py
