Metadata-Version: 2.0
Name: pygtails
Version: 0.1.6
Summary: A simple wrapper around pygame
Home-page: http://pygtails.readthedocs.io/en/latest/
Author: Josie Thompson
Author-email: UNKNOWN
License: UNKNOWN
Project-URL: Source, https://github.com/josiest/pygtails/
Platform: UNKNOWN
Classifier: Development Status :: 1 - Planning
Classifier: Intended Audience :: Developers
Classifier: License :: OSI Approved :: MIT License
Classifier: Natural Language :: English
Classifier: Programming Language :: Python :: 3 :: Only
Classifier: Topic :: Software Development :: Libraries :: pygame
Requires-Python: >=3
